lslgwserver/__init__.py
lslgwserver/auth/__init__.py
lslgwserver/auth/auth.py
lslgwserver/auth/container.py
lslgwserver/enums/__init__.py
lslgwserver/enums/liksetdata.py
lslgwserver/models/__init__.py
lslgwserver/models/linksetdata.py
lslgwserver/models/lslrequest.py
lslgwserver/py.typed
lslgwserver/routers/__init__.py
lslgwserver/routers/attached.py
lslgwserver/routers/changed.py
lslgwserver/routers/chatmessage.py
lslgwserver/routers/linkmessage.py
lslgwserver/routers/linksetdata.py
lslgwserver/routers/money.py
lslgwserver/routers/router.py
lslgwserver/routers/touch.py
lsl_gateway_server-24.8.0.dist-info/LICENSE-lgpl-3.0.md
lsl_gateway_server-24.8.0.dist-info/METADATA
lsl_gateway_server-24.8.0.dist-info/WHEEL
lsl_gateway_server-24.8.0.dist-info/RECORD
